nancal_langchain_base/__init__.py
nancal_langchain_base/main.py
nancal_langchain_base/common/__init__.py
nancal_langchain_base/common/main_utils.py
nancal_langchain_base/error/__init__.py
nancal_langchain_base/error/ckassifier.py
nancal_langchain_base/error/codes.py
nancal_langchain_base/error/exceptions.py
nancal_langchain_base/error/test_classifier.py
nancal_langchain_base/file/__init__.py
nancal_langchain_base/file/file.py
nancal_langchain_base/global_conf/__init__.py
nancal_langchain_base/global_conf/context.py
nancal_langchain_base/global_conf/global_config.py
nancal_langchain_base/global_conf/initialize_config.py
nancal_langchain_base/helper/__init__.py
nancal_langchain_base/helper/agent_config_helper.py
nancal_langchain_base/helper/agent_helper.py
nancal_langchain_base/helper/graph_helper.py
nancal_langchain_base/log/__init__.py
nancal_langchain_base/log/common.py
nancal_langchain_base/log/config.py
nancal_langchain_base/log/err_trace.py
nancal_langchain_base/log/loop_trace.py
nancal_langchain_base/log/node_log.py
nancal_langchain_base/log/parser.py
nancal_langchain_base/log/write_log.py
nancal_langchain_base/messages/__init__.py
nancal_langchain_base/messages/client.py
nancal_langchain_base/messages/server.py
nancal_langchain_base/model_clients/__init__.py
nancal_langchain_base/model_clients/config.py
nancal_langchain_base/model_clients/exceptions.py
nancal_langchain_base/model_clients/llm.py
nancal_langchain_base/model_clients/models.py
nancal_langchain_base-0.1.6.dist-info/METADATA
nancal_langchain_base-0.1.6.dist-info/WHEEL
nancal_langchain_base-0.1.6.dist-info/top_level.txt
nancal_langchain_base-0.1.6.dist-info/RECORD
